odoo/addons/currency_rate_update_RO_BNR/README.rst
odoo/addons/currency_rate_update_RO_BNR/__init__.py
odoo/addons/currency_rate_update_RO_BNR/__manifest__.py
odoo/addons/currency_rate_update_RO_BNR/i18n/currency_rate_update_RO_BNR.pot
odoo/addons/currency_rate_update_RO_BNR/models/__init__.py
odoo/addons/currency_rate_update_RO_BNR/models/res_currency_rate_provider_RO_BNR.py
odoo/addons/currency_rate_update_RO_BNR/readme/CONTRIBUTORS.rst
odoo/addons/currency_rate_update_RO_BNR/readme/DESCRIPTION.rst
odoo/addons/currency_rate_update_RO_BNR/readme/INSTALL.rst
odoo/addons/currency_rate_update_RO_BNR/readme/USAGE.rst
odoo/addons/currency_rate_update_RO_BNR/static/description/icon.png
odoo/addons/currency_rate_update_RO_BNR/static/description/index.html
odoo/addons/currency_rate_update_RO_BNR/tests/__init__.py
odoo/addons/currency_rate_update_RO_BNR/tests/test_currency_rate_update_ro_bnr.py
odoo13_addon_currency_rate_update_RO_BNR-13.0.2.0.2.dist-info/METADATA
odoo13_addon_currency_rate_update_RO_BNR-13.0.2.0.2.dist-info/WHEEL
odoo13_addon_currency_rate_update_RO_BNR-13.0.2.0.2.dist-info/top_level.txt
odoo13_addon_currency_rate_update_RO_BNR-13.0.2.0.2.dist-info/RECORD
