Metadata-Version: 2.1
Name: odoo13-addon-currency-rate-update-RO-BNR
Version: 13.0.2.0.2
Summary: Currency Rate Update National Bank of Romania service
Home-page: https://github.com/OCA/l10n-romania
Author: NextERP Romania,Forest and Biomass Romania,Odoo Community Association (OCA)
Author-email: support@odoo-community.org
License: AGPL-3
Platform: UNKNOWN
Classifier: Programming Language :: Python
Classifier: Framework :: Odoo
Classifier: License :: OSI Approved :: GNU Affero General Public License v3
Classifier: Development Status :: 6 - Mature
Requires-Python: >=3.5
Requires-Dist: odoo13-addon-currency-rate-update
Requires-Dist: odoo (<13.1dev,>=13.0a)
